dovesnap/__init__.py
dovesnap/cleanup_dovesnap
dovesnap/graph_dovesnap.py
dovesnap-1.1.23.dist-info/LICENSE
dovesnap-1.1.23.dist-info/METADATA
dovesnap-1.1.23.dist-info/WHEEL
dovesnap-1.1.23.dist-info/entry_points.txt
dovesnap-1.1.23.dist-info/RECORD
