Metadata-Version: 2.1
Name: dovesnap
Version: 1.1.23
Summary: graphviz generator of dovesnap networks
License: Apache-2.0
Author: Charlie Lewis
Author-email: clewis@iqt.org
Requires-Python: >=3.9,<3.12
Classifier: License :: OSI Approved :: Apache Software License
Classifier: Programming Language :: Python :: 3
Classifier: Programming Language :: Python :: 3.9
Classifier: Programming Language :: Python :: 3.10
Classifier: Programming Language :: Python :: 3.11
Requires-Dist: docker (==7.0.0)
Requires-Dist: faucetconfrpc (==0.55.68)
Requires-Dist: graphviz (==0.20.1)
Requires-Dist: ruamel.yaml (>=0.18.2,<0.19.0)
Project-URL: homepage, https://github.com/IQTLabs/dovesnap
